autodistill_rfdetr/__init__.py
autodistill_rfdetr/model.py
autodistill_rfdetr-0.1.0.dist-info/METADATA
autodistill_rfdetr-0.1.0.dist-info/WHEEL
autodistill_rfdetr-0.1.0.dist-info/top_level.txt
autodistill_rfdetr-0.1.0.dist-info/RECORD
