Metadata-Version: 2.4
Name: autodistill-rfdetr
Version: 0.1.0
Summary: RF-DETR model for use with Autodistill
Home-page: https://github.com/autodistill/autodistill-rfdetr
Author: Roboflow
Author-email: support@roboflow.com
Classifier: Programming Language :: Python :: 3
Classifier: License :: OSI Approved :: MIT License
Classifier: Operating System :: OS Independent
Requires-Python: >=3.7
Requires-Dist: rfdetr
Requires-Dist: autodistill
Provides-Extra: dev
Requires-Dist: flake8; extra == "dev"
Requires-Dist: black==22.3.0; extra == "dev"
Requires-Dist: isort; extra == "dev"
Requires-Dist: twine; extra == "dev"
Requires-Dist: pytest; extra == "dev"
Requires-Dist: wheel; extra == "dev"
Dynamic: author
Dynamic: author-email
Dynamic: classifier
Dynamic: description
Dynamic: description-content-type
Dynamic: home-page
Dynamic: provides-extra
Dynamic: requires-dist
Dynamic: requires-python
Dynamic: summary
